pypearl/__init__.py
pypearl/__init__.pyi
pypearl/_pypearl.cpython-313-darwin.so
pypearl/main.py
pypearl/py.typed
pypearl-0.7.10.dist-info/licenses/LICENSE
pypearl-0.7.10.dist-info/METADATA
pypearl-0.7.10.dist-info/WHEEL
pypearl-0.7.10.dist-info/top_level.txt
pypearl-0.7.10.dist-info/RECORD
