Metadata-Version: 2.4
Name: pypearl
Version: 0.7.10
Summary: An efficient Machine Learning Library
Author: Brody Massad
Author-email: brodymassad@gmail.com
Requires-Python: >=3.7
License-File: LICENSE
Dynamic: author
Dynamic: author-email
Dynamic: description
Dynamic: description-content-type
Dynamic: license-file
Dynamic: requires-python
Dynamic: summary
